DISTRIBUTION
LICENSE
MANIFEST.in
README.md
VERSION
environment.yml
environment_xnrl.yml
setup.cfg
setup.py
xnrl/__init__.py
xnrl/cli.py
xnrl/compute.py
xnrl/constant.py
xnrl/flatfile.py
xnrl/generic.py
xnrl/grads.py
xnrl/grib.py
xnrl/hdf5.py
xnrl/internal.py
xnrl/io.py
xnrl/main.py
xnrl/netcdf.py
xnrl/packages.py
xnrl/plot.py
xnrl/select.py
xnrl/tutorial.py
xnrl/util.py
xnrl/visual.py
xnrl.egg-info/PKG-INFO
xnrl.egg-info/SOURCES.txt
xnrl.egg-info/dependency_links.txt
xnrl.egg-info/entry_points.txt
xnrl.egg-info/not-zip-safe
xnrl.egg-info/requires.txt
xnrl.egg-info/top_level.txt