Metadata-Version: 2.1
Name: xnrl
Version: 2022.9.29
Summary: xNRL - Read NRL files into xarray Datasets nested within pandas DataFrames
Keywords: flatfile,nrl,xarray,dataset,binary,hdf5,grib
License-File: LICENSE
